MANIFEST.in
README.rst
setup.py
djmo/__init__.py
djmo/decorators.py
djmo/observer.py
djmo.egg-info/PKG-INFO
djmo.egg-info/SOURCES.txt
djmo.egg-info/dependency_links.txt
djmo.egg-info/not-zip-safe
djmo.egg-info/requires.txt
djmo.egg-info/top_level.txt