Metadata-Version: 1.1
Name: djmo
Version: 0.0.1
Summary: Django Model Observer
Home-page: https://github.com/griffosx/dj-model-observer
Author: Davide Giuseppe Griffon
Author-email: davide.griffon@gmail.com
License: MIT
Keywords: django test utility
Platform: UNKNOWN
Classifier: Development Status :: 4 - Beta
Classifier: Framework :: Django
Classifier: License :: OSI Approved :: MIT License
Classifier: Programming Language :: Python :: 3 :: Only
Classifier: Topic :: Software Development :: Testing
